CHANGES
LICENSE
MANIFEST.in
README.rst
setup.cfg
setup.py
sphinxcontrib/__init__.py
sphinxcontrib/ditaa.py
sphinxcontrib_ditaa.egg-info/PKG-INFO
sphinxcontrib_ditaa.egg-info/SOURCES.txt
sphinxcontrib_ditaa.egg-info/dependency_links.txt
sphinxcontrib_ditaa.egg-info/namespace_packages.txt
sphinxcontrib_ditaa.egg-info/requires.txt
sphinxcontrib_ditaa.egg-info/top_level.txt