Metadata-Version: 1.0
Name: sphinxcontrib-ditaa
Version: 0.3
Summary: Ditaa Sphinx extension
Home-page: https://github.com/stathissideris/ditaa
Author: Yongping Guo
Author-email: guoyoooping@163.com
License: BSD
Platform: any
